LICENSE
MANIFEST.in
README.rst
setup.py
arango/CHANGELOG
arango/__init__.py
arango/__init__.pyc
arango/aql.py
arango/aql.pyc
arango/async.py
arango/collection.py
arango/collection.pyc
arango/comparsion.pyc
arango/core.py
arango/core.pyc
arango/cursor.py
arango/cursor.pyc
arango/db.py
arango/db.pyc
arango/document.py
arango/document.pyc
arango/edge.py
arango/edge.pyc
arango/exceptions.py
arango/exceptions.pyc
arango/index.py
arango/index.pyc
arango/mixins.py
arango/mixins.pyc
arango/utils.py
arango/utils.pyc
arango.egg-info/PKG-INFO
arango.egg-info/SOURCES.txt
arango.egg-info/dependency_links.txt
arango.egg-info/requires.txt
arango.egg-info/top_level.txt
arango/__pycache__/__init__.cpython-33.pyc
arango/__pycache__/aql.cpython-33.pyc
arango/__pycache__/collection.cpython-33.pyc
arango/__pycache__/core.cpython-33.pyc
arango/__pycache__/cursor.cpython-33.pyc
arango/__pycache__/db.cpython-33.pyc
arango/__pycache__/document.cpython-33.pyc
arango/__pycache__/edge.cpython-33.pyc
arango/__pycache__/exceptions.cpython-33.pyc
arango/__pycache__/index.cpython-33.pyc
arango/__pycache__/mixins.cpython-33.pyc
arango/__pycache__/utils.cpython-33.pyc
arango/clients/__init__.py
arango/clients/__init__.pyc
arango/clients/base.py
arango/clients/base.pyc
arango/clients/pycurlclient.py
arango/clients/pycurlclient.pyc
arango/clients/requestsclient.py
arango/clients/requestsclient.pyc
arango/clients/urllib2client.py
arango/clients/urllib2client.pyc
arango/clients/__pycache__/__init__.cpython-33.pyc
arango/clients/__pycache__/base.cpython-33.pyc
arango/clients/__pycache__/pycurlclient.cpython-33.pyc
arango/clients/__pycache__/requestsclient.cpython-33.pyc
arango/clients/__pycache__/urllib2client.cpython-33.pyc
arango/tests/__init__.py
arango/tests/__init__.pyc
arango/tests/tests_aql.py
arango/tests/tests_aql.pyc
arango/tests/tests_base.py
arango/tests/tests_base.pyc
arango/tests/tests_collection.py
arango/tests/tests_collection.pyc
arango/tests/tests_collection_integration.py
arango/tests/tests_collection_integration.pyc
arango/tests/tests_core.py
arango/tests/tests_core.pyc
arango/tests/tests_core_integration.py
