Metadata-Version: 1.1
Name: arango
Version: 0.2.1
Summary: Driver for ArangoDB
Home-page: http://arangodb-python-driver.readthedocs.org/en/latest/
Author: Maksym Klymyshyn
Author-email: klymyshyn@gmail.com
License: UNKNOWN
Platform: UNKNOWN
Classifier: Topic :: Database
Classifier: Development Status :: 4 - Beta
Classifier: Intended Audience :: Developers
Classifier: Operating System :: OS Independent
Classifier: Programming Language :: Python
Classifier: Programming Language :: Python :: 2.7
Classifier: Programming Language :: Python :: 3.3
